pystack3d_napari/__init__.py
pystack3d_napari/main.py
pystack3d_napari/utils.py
pystack3d_napari/widgets.py
pystack3d_napari-2025.1.dist-info/METADATA
pystack3d_napari-2025.1.dist-info/WHEEL
pystack3d_napari-2025.1.dist-info/entry_points.txt
pystack3d_napari-2025.1.dist-info/top_level.txt
pystack3d_napari-2025.1.dist-info/RECORD
