Metadata-Version: 2.4
Name: pystack3d_napari
Version: 2025.1
Summary: Pystack3D-napari: A Python package for fast image stack correction with its dedicated GUI
Author-email: Patrick Quéméré <patrick.quemere@cea.fr>
License: GPL v3
Project-URL: Repository, https://github.com/CEA-MetroCarac/pystack3d_napari.git
Project-URL: Issues, https://github.com/CEA-MetroCarac/pystack3d_napari/issues
Classifier: Development Status :: 4 - Beta
Classifier: Intended Audience :: Developers
Classifier: Framework :: napari
Classifier: Topic :: Software Development :: Testing
Classifier: Programming Language :: Python
Classifier: Programming Language :: Python :: 3 :: Only
Classifier: Programming Language :: Python :: 3.10
Classifier: Programming Language :: Python :: 3.11
Classifier: Programming Language :: Python :: 3.12
Classifier: Programming Language :: Python :: 3.13
Classifier: Operating System :: OS Independent
Classifier: License :: OSI Approved :: Apache Software License
Requires-Python: >=3.10
Requires-Dist: napari
Requires-Dist: dask[array]
Requires-Dist: numba
Requires-Dist: pystack3d
